setup.py
asposeimagingcloud/ApiClient.py
asposeimagingcloud/ImagingApi.py
asposeimagingcloud/__init__.py
asposeimagingcloud.egg-info/PKG-INFO
asposeimagingcloud.egg-info/SOURCES.txt
asposeimagingcloud.egg-info/dependency_links.txt
asposeimagingcloud.egg-info/requires.txt
asposeimagingcloud.egg-info/top_level.txt
asposeimagingcloud/models/BmpProperties.py
asposeimagingcloud/models/ExifData.py
asposeimagingcloud/models/GifProperties.py
asposeimagingcloud/models/ImagingResponse.py
asposeimagingcloud/models/JfifData.py
asposeimagingcloud/models/JpegExifData.py
asposeimagingcloud/models/JpegProperties.py
asposeimagingcloud/models/PngProperties.py
asposeimagingcloud/models/PsdProperties.py
asposeimagingcloud/models/ResponseMessage.py
asposeimagingcloud/models/SaaSposeResponse.py
asposeimagingcloud/models/TiffProperties.py
asposeimagingcloud/models/__init__.py
tests/__init__.py
tests/test_ImagingApi.py